satpy/__init__.py
satpy/_compat.py
satpy/_config.py
satpy/_scene_converters.py
satpy/area.py
satpy/aux_download.py
satpy/conftest.py
satpy/coords.py
satpy/decision_tree.py
satpy/dependency_tree.py
satpy/node.py
satpy/plugin_base.py
satpy/py.typed
satpy/scene.py
satpy/testing.py
satpy/utils.py
satpy/version.py
satpy/cf/__init__.py
satpy/cf/area.py
satpy/cf/attrs.py
satpy/cf/coords.py
satpy/cf/data_array.py
satpy/cf/datasets.py
satpy/cf/decoding.py
satpy/cf/encoding.py
satpy/composites/__init__.py
satpy/composites/abi.py
satpy/composites/agri.py
satpy/composites/ahi.py
satpy/composites/arithmetic.py
satpy/composites/aux_data.py
satpy/composites/cloud_products.py
satpy/composites/config_loader.py
satpy/composites/core.py
satpy/composites/fill.py
satpy/composites/glm.py
satpy/composites/lightning.py
satpy/composites/lookup.py
satpy/composites/mask.py
satpy/composites/resolution.py
satpy/composites/sar.py
satpy/composites/seviri.py
satpy/composites/spectral.py
satpy/composites/viirs.py
satpy/dataset/__init__.py
satpy/dataset/anc_vars.py
satpy/dataset/data_dict.py
satpy/dataset/dataid.py
satpy/dataset/metadata.py
satpy/demo/__init__.py
satpy/demo/_google_cloud_platform.py
satpy/demo/abi_l1b.py
satpy/demo/ahi_hsd.py
satpy/demo/fci.py
satpy/demo/seviri_hrit.py
satpy/demo/utils.py
satpy/demo/viirs_sdr.py
satpy/enhancements/__init__.py
satpy/enhancements/abi.py
satpy/enhancements/ahi.py
satpy/enhancements/colormap.py
satpy/enhancements/contrast.py
satpy/enhancements/convolution.py
satpy/enhancements/enhancer.py
satpy/enhancements/mimic.py
satpy/enhancements/overlays.py
satpy/enhancements/viirs.py
satpy/enhancements/wrappers.py
satpy/etc/areas.yaml
satpy/etc/eps_avhrrl1b_6.5.xml
satpy/etc/ninjo-cmd.yaml
satpy/etc/composites/abi.yaml
satpy/etc/composites/agri.yaml
satpy/etc/composites/ahi.yaml
satpy/etc/composites/ami.yaml
satpy/etc/composites/amsr2.yaml
satpy/etc/composites/atms.yaml
satpy/etc/composites/avhrr-3.yaml
satpy/etc/composites/ec_msi.yaml
satpy-0.59.0.dist-info/METADATA
satpy-0.59.0.dist-info/WHEEL
satpy-0.59.0.dist-info/entry_points.txt
satpy-0.59.0.dist-info/licenses/AUTHORS.md
satpy-0.59.0.dist-info/licenses/LICENSE.txt
satpy-0.59.0.dist-info/RECORD
