Metadata-Version: 2.4
Name: satpy
Version: 0.59.0
Summary: Python package for earth-observing satellite data processing
Project-URL: Homepage, https://github.com/pytroll/satpy
Project-URL: Bug Tracker, https://github.com/pytroll/satpy/issues
Project-URL: Documentation, https://satpy.readthedocs.io/en/stable/
Project-URL: Source Code, https://github.com/pytroll/satpy
Project-URL: Organization, https://pytroll.github.io/
Project-URL: Slack, https://pytroll.slack.com/
Project-URL: Twitter, https://twitter.com/hashtag/satpy?src=hashtag_click
Project-URL: Release Notes, https://github.com/pytroll/satpy/blob/main/CHANGELOG.md
Project-URL: Mastodon, https://fosstodon.org/tags/satpy
Author-email: The Pytroll Team <pytroll@googlegroups.com>
License: GPLv3
License-File: AUTHORS.md
License-File: LICENSE.txt
Classifier: Development Status :: 5 - Production/Stable
Classifier: Intended Audience :: Science/Research
Classifier: License :: OSI Approved :: GNU General Public License v3 or later (GPLv3+)
Classifier: Operating System :: OS Independent
Classifier: Programming Language :: Python
Classifier: Topic :: Scientific/Engineering
Requires-Python: >=3.10
Requires-Dist: dask[array]>=0.17.1
Requires-Dist: donfig
Requires-Dist: numpy>=1.21
Requires-Dist: packaging
Requires-Dist: pillow
Requires-Dist: platformdirs
Requires-Dist: pooch
Requires-Dist: pykdtree
Requires-Dist: pyorbital
Requires-Dist: pyproj>=2.2
Requires-Dist: pyresample>=1.24.0
Requires-Dist: pyyaml>=5.1
Requires-Dist: trollimage>=1.24
Requires-Dist: trollsift
Requires-Dist: universal-pathlib
Requires-Dist: xarray>=0.14.1
Requires-Dist: zarr
Provides-Extra: abi-l1b
Requires-Dist: h5netcdf; extra == 'abi-l1b'
Provides-Extra: acspo
Requires-Dist: netcdf4>=1.1.8; extra == 'acspo'
Provides-Extra: amsr2-l1b
Requires-Dist: h5py>=2.7.0; extra == 'amsr2-l1b'
Provides-Extra: angles
Requires-Dist: pyorbital>=1.3.1; extra == 'angles'
Provides-Extra: animations
Requires-Dist: imageio; extra == 'animations'
Provides-Extra: avhrr-l1b-eps
Requires-Dist: defusedxml; extra == 'avhrr-l1b-eps'
Provides-Extra: avhrr-l1b-gaclac
Requires-Dist: pygac>=1.3.0; extra == 'avhrr-l1b-gaclac'
Provides-Extra: awips-tiled
Requires-Dist: netcdf4>=1.1.8; extra == 'awips-tiled'
Provides-Extra: cf
Requires-Dist: h5netcdf>=0.7.3; extra == 'cf'
Provides-Extra: clavrx
Requires-Dist: netcdf4>=1.1.8; extra == 'clavrx'
Provides-Extra: dev
Requires-Dist: astropy; extra == 'dev'
Requires-Dist: behave; extra == 'dev'
Requires-Dist: bottleneck; extra == 'dev'
Requires-Dist: dask-image; extra == 'dev'
Requires-Dist: defusedxml; extra == 'dev'
Requires-Dist: eccodes; extra == 'dev'
Requires-Dist: ephem; extra == 'dev'
Requires-Dist: fsspec; extra == 'dev'
Requires-Dist: geoviews; extra == 'dev'
Requires-Dist: h5netcdf; extra == 'dev'
Requires-Dist: h5py; extra == 'dev'
Requires-Dist: imageio; extra == 'dev'
Requires-Dist: netcdf4; extra == 'dev'
Requires-Dist: numba; extra == 'dev'
Requires-Dist: pint-xarray; extra == 'dev'
Requires-Dist: pyhdf; extra == 'dev'
Requires-Dist: pytest; extra == 'dev'
Requires-Dist: pytest-lazy-fixtures; extra == 'dev'
Requires-Dist: python-geotiepoints; extra == 'dev'
Requires-Dist: rasterio; extra == 'dev'
Requires-Dist: rioxarray; extra == 'dev'
Requires-Dist: s3fs; extra == 'dev'
Requires-Dist: skyfield; extra == 'dev'
Requires-Dist: sphinx; extra == 'dev'
Requires-Dist: sphinx-rtd-theme; extra == 'dev'
Requires-Dist: sphinxcontrib-apidoc; extra == 'dev'
Requires-Dist: trollimage; extra == 'dev'
Requires-Dist: xarray>=2024.10.0; extra == 'dev'
Provides-Extra: doc
Requires-Dist: sphinx; extra == 'doc'
Requires-Dist: sphinx-rtd-theme; extra == 'doc'
Requires-Dist: sphinxcontrib-apidoc; extra == 'doc'
Provides-Extra: filters
Requires-Dist: dask-image; extra == 'filters'
Provides-Extra: generic-image
Requires-Dist: rasterio; extra == 'generic-image'
Requires-Dist: rioxarray; extra == 'generic-image'
Provides-Extra: geocat
Requires-Dist: pyhdf; extra == 'geocat'
Provides-Extra: geotiff
Requires-Dist: rasterio; extra == 'geotiff'
Requires-Dist: trollimage[geotiff]; extra == 'geotiff'
Provides-Extra: geoviews
Requires-Dist: geoviews; extra == 'geoviews'
Provides-Extra: gms5-vissr-l1b
Requires-Dist: numba; extra == 'gms5-vissr-l1b'
Provides-Extra: goci2
Requires-Dist: netcdf4>=1.1.8; extra == 'goci2'
Provides-Extra: holoviews
Requires-Dist: holoviews; extra == 'holoviews'
Provides-Extra: hrit-msg
Requires-Dist: pytroll-schedule; extra == 'hrit-msg'
Provides-Extra: hrpt
Requires-Dist: pygac; extra == 'hrpt'
Requires-Dist: pyorbital>=1.3.1; extra == 'hrpt'
Requires-Dist: python-geotiepoints>=1.1.7; extra == 'hrpt'
Provides-Extra: hsaf-grib
Requires-Dist: pygrib; extra == 'hsaf-grib'
Provides-Extra: hvplot
Requires-Dist: cartopy; extra == 'hvplot'
Requires-Dist: geoviews; extra == 'hvplot'
Requires-Dist: holoviews; extra == 'hvplot'
Requires-Dist: hvplot; extra == 'hvplot'
Provides-Extra: insat-3d
Requires-Dist: xarray>=2024.10.0; extra == 'insat-3d'
Provides-Extra: modis-l1b
Requires-Dist: pyhdf; extra == 'modis-l1b'
Requires-Dist: python-geotiepoints>=1.1.7; extra == 'modis-l1b'
Provides-Extra: msi-safe
Requires-Dist: bottleneck; extra == 'msi-safe'
Requires-Dist: defusedxml; extra == 'msi-safe'
Requires-Dist: python-geotiepoints; extra == 'msi-safe'
Requires-Dist: rioxarray; extra == 'msi-safe'
Provides-Extra: nc-nwcsaf-msg
Requires-Dist: netcdf4>=1.1.8; extra == 'nc-nwcsaf-msg'
Provides-Extra: ninjo
Requires-Dist: pint; extra == 'ninjo'
Requires-Dist: pyninjotiff; extra == 'ninjo'
Provides-Extra: omps-edr
Requires-Dist: h5py>=2.7.0; extra == 'omps-edr'
Provides-Extra: overlays
Requires-Dist: pycoast; extra == 'overlays'
Requires-Dist: pydecorate; extra == 'overlays'
Provides-Extra: rayleigh
Requires-Dist: pyspectral>=0.10.1; extra == 'rayleigh'
Provides-Extra: remote-reading
Requires-Dist: fsspec; extra == 'remote-reading'
Provides-Extra: sar-c
Requires-Dist: defusedxml; extra == 'sar-c'
Requires-Dist: python-geotiepoints>=1.1.7; extra == 'sar-c'
Requires-Dist: rasterio; extra == 'sar-c'
Requires-Dist: rioxarray; extra == 'sar-c'
Provides-Extra: satpos-from-tle
Requires-Dist: astropy; extra == 'satpos-from-tle'
Requires-Dist: skyfield; extra == 'satpos-from-tle'
Provides-Extra: seviri-l1b-hrit
Requires-Dist: pyorbital>=1.3.1; extra == 'seviri-l1b-hrit'
Requires-Dist: pypublicdecompwt; extra == 'seviri-l1b-hrit'
Provides-Extra: seviri-l1b-native
Requires-Dist: pyorbital>=1.3.1; extra == 'seviri-l1b-native'
Provides-Extra: seviri-l1b-nc
Requires-Dist: netcdf4>=1.1.8; extra == 'seviri-l1b-nc'
Requires-Dist: pyorbital>=1.3.1; extra == 'seviri-l1b-nc'
Provides-Extra: seviri-l2-bufr
Requires-Dist: eccodes; extra == 'seviri-l2-bufr'
Provides-Extra: seviri-l2-grib
Requires-Dist: eccodes; extra == 'seviri-l2-grib'
Provides-Extra: tests
Requires-Dist: astropy; extra == 'tests'
Requires-Dist: behave; extra == 'tests'
Requires-Dist: bottleneck; extra == 'tests'
Requires-Dist: dask-image; extra == 'tests'
Requires-Dist: defusedxml; extra == 'tests'
Requires-Dist: eccodes; extra == 'tests'
Requires-Dist: ephem; extra == 'tests'
Requires-Dist: fsspec; extra == 'tests'
Requires-Dist: geoviews; extra == 'tests'
Requires-Dist: h5netcdf; extra == 'tests'
Requires-Dist: h5py; extra == 'tests'
Requires-Dist: imageio; extra == 'tests'
Requires-Dist: netcdf4; extra == 'tests'
Requires-Dist: numba; extra == 'tests'
Requires-Dist: pint-xarray; extra == 'tests'
Requires-Dist: pyhdf; extra == 'tests'
Requires-Dist: pytest; extra == 'tests'
Requires-Dist: pytest-lazy-fixtures; extra == 'tests'
Requires-Dist: python-geotiepoints; extra == 'tests'
Requires-Dist: rasterio; extra == 'tests'
Requires-Dist: rioxarray; extra == 'tests'
Requires-Dist: s3fs; extra == 'tests'
Requires-Dist: skyfield; extra == 'tests'
Requires-Dist: trollimage; extra == 'tests'
Requires-Dist: xarray>=2024.10.0; extra == 'tests'
Provides-Extra: units
Requires-Dist: pint-xarray; extra == 'units'
Provides-Extra: vii-l1b
Requires-Dist: python-geotiepoints; extra == 'vii-l1b'
Provides-Extra: viirs-compact
Requires-Dist: h5py>=2.7.0; extra == 'viirs-compact'
Provides-Extra: viirs-l1b
Requires-Dist: netcdf4>=1.1.8; extra == 'viirs-l1b'
Provides-Extra: viirs-sdr
Requires-Dist: h5py>=2.7.0; extra == 'viirs-sdr'
